pandocfilters_sh/__init__.py
pandocfilters_sh/__main__.py
pandocfilter_sh-0.1.dist-info/METADATA
pandocfilter_sh-0.1.dist-info/WHEEL
pandocfilter_sh-0.1.dist-info/entry_points.txt
pandocfilter_sh-0.1.dist-info/top_level.txt
pandocfilter_sh-0.1.dist-info/RECORD
